example_package_cstashko/__init__.py
example_package_cstashko/example.py
example_package_cstashko/misc.py
example_package_cstashko-0.0.11.dist-info/METADATA
example_package_cstashko-0.0.11.dist-info/WHEEL
example_package_cstashko-0.0.11.dist-info/licenses/LICENSE
example_package_cstashko-0.0.11.dist-info/RECORD
